ironshield/__init__.py
ironshield/cli.py
ironshield-0.0.1.dist-info/METADATA
ironshield-0.0.1.dist-info/WHEEL
ironshield-0.0.1.dist-info/entry_points.txt
ironshield-0.0.1.dist-info/top_level.txt
ironshield-0.0.1.dist-info/RECORD
