Metadata-Version: 2.4
Name: ironshield
Version: 0.0.1
Summary: IronShield - A comprehensive security toolkit for Python applications
Home-page: https://github.com/IronShield-Tech/ironshield-js
Author: IronShield Tech
Author-email: IronShield Tech <tech@ironshield.dev>
License: ISC
Project-URL: Homepage, https://github.com/IronShield-Tech/ironshield-js
Project-URL: Bug Reports, https://github.com/IronShield-Tech/ironshield-js/issues
Project-URL: Source, https://github.com/IronShield-Tech/ironshield-js
Keywords: security,ironshield,protection,python,security-toolkit
Classifier: Development Status :: 2 - Pre-Alpha
Classifier: Intended Audience :: Developers
Classifier: Topic :: Security
Classifier: Topic :: Software Development :: Libraries :: Python Modules
Classifier: License :: OSI Approved :: ISC License (ISCL)
Classifier: Programming Language :: Python :: 3
Classifier: Programming Language :: Python :: 3.7
Classifier: Programming Language :: Python :: 3.8
Classifier: Programming Language :: Python :: 3.9
Classifier: Programming Language :: Python :: 3.10
Classifier: Programming Language :: Python :: 3.11
Classifier: Programming Language :: Python :: 3.12
Requires-Python: >=3.7
Provides-Extra: dev
Requires-Dist: pytest>=6.0; extra == "dev"
Requires-Dist: black; extra == "dev"
Requires-Dist: flake8; extra == "dev"
Dynamic: author
Dynamic: home-page
Dynamic: requires-python
